vimeodlpy/__init__.py
vimeodlpy/cli.py
vimeodlpy/downloader.py
vimeodlpy/exceptions.py
vimeodlpy/logger.py
vimeodlpy/parser.py
vimeodlpy/utils.py
vimeodlpy-0.1.0.dist-info/entry_points.txt
vimeodlpy-0.1.0.dist-info/LICENSE
vimeodlpy-0.1.0.dist-info/METADATA
vimeodlpy-0.1.0.dist-info/WHEEL
vimeodlpy-0.1.0.dist-info/RECORD
