Metadata-Version: 2.3
Name: vimeodlpy
Version: 0.1.0
Summary: A lightweight Python library and CLI to download Vimeo videos using FFmpeg.
License: Apache-2.0
Keywords: vimeo,downloader,ffmpeg,cli,video,stream
Author: moijesuis2enmoi
Author-email: arm.ag.31415@gmail.com
Requires-Python: >=3.11
Classifier: License :: OSI Approved :: Apache Software License
Classifier: Programming Language :: Python :: 3
Classifier: Programming Language :: Python :: 3.11
Classifier: Programming Language :: Python :: 3.12
Classifier: Programming Language :: Python :: 3.13
Requires-Dist: beautifulsoup4 (>=4.12.0,<5.0.0)
Requires-Dist: cloudscraper (>=1.2.71,<2.0.0)
Requires-Dist: ffmpeg-python (>=0.2.0,<0.3.0)
Requires-Dist: tqdm (>=4.67.1,<5.0.0)
Requires-Dist: typer (>=0.16.0,<0.17.0)
Project-URL: Documentation, https://github.com/moijesuis2enmoi/vimeodlpy#readme
Project-URL: Homepage, https://github.com/moijesuis2enmoi/vimeodlpy
Project-URL: Issue Tracker, https://github.com/moijesuis2enmoi/vimeodlpy/issues
Project-URL: Repository, https://github.com/moijesuis2enmoi/vimeodlpy
